.gitignore
CITATION
CODE_OF_CONDUCT.md
ETCSERVER.BAT
LICENSE.md
MANIFEST.in
README.rst
ROADMAP.md
pyproject.toml
setup.cfg
setup.py
.github/workflows/ci_workflows.yml
.github/workflows/publish-to-pypi.yml
commissioning/SETENV.csh
commissioning/SETENV_MINE.csh
commissioning/SETENV_PINNED.csh
commissioning/acs_effstim_cases.py
commissioning/acs_effstim_cases.txt
commissioning/acs_etc_cases.py
commissioning/acs_etc_cases.txt
commissioning/acs_etc_cases_subset.txt
commissioning/acs_rn_cases.py
commissioning/acs_rn_cases.txt
commissioning/apply_overlap.py
commissioning/apply_overlap_input.txt
commissioning/basecase.py
commissioning/casestats.csh
commissioning/commissioning_report.txt
commissioning/comparison.txt
commissioning/dodiags.csh
commissioning/doscalars.py
commissioning/effstim_from_rn.py
commissioning/errors.txt
commissioning/finderror.csh
commissioning/gencases.py
commissioning/genscience.py
commissioning/invalid_rn_cases.py
commissioning/kwfile_dict.py
commissioning/makehist.py
commissioning/nicmos_effstim_cases.py
commissioning/nicmos_effstim_cases.txt
commissioning/nicmos_etc_cases.py
commissioning/nicmos_etc_cases.txt
commissioning/nicmos_etc_cases_subset.txt
commissioning/nicmos_etc_thermback_cases.py
commissioning/nicmos_etc_thermback_cases.txt
commissioning/nicmos_rn_cases.py
commissioning/nicmos_rn_cases.txt
commissioning/platform_cases.py
commissioning/preprocess_rn_cases.py
commissioning/printversion.py
commissioning/process_wfc3.csh
commissioning/processlog.csh
commissioning/readme.txt
commissioning/runplatform.csh
commissioning/runset.csh
commissioning/runversion.csh
commissioning/science_cases.py
commissioning/status_16jun.txt
commissioning/stis_effstim_cases.py
commissioning/stis_effstim_cases.txt
commissioning/stis_etc_cases.py
commissioning/stis_etc_cases.txt
commissioning/stis_etc_cases_subset.txt
commissioning/stis_rn_cases.py
commissioning/stis_rn_cases.txt
commissioning/updated_testdata.txt
commissioning/wfc3_ir_imaging_78_cases.py
pysynphot.egg-info/PKG-INFO
pysynphot.egg-info/SOURCES.txt
pysynphot.egg-info/dependency_links.txt
pysynphot.egg-info/not-zip-safe
pysynphot.egg-info/requires.txt
pysynphot.egg-info/top_level.txt
