Metadata-Version: 2.1
Name: pysynphot
Version: 2.0.0
Summary: Python Synthetic Photometry Utilities
Home-page: https://github.com/spacetelescope/pysynphot
Author: Vicki Laidler, Pey Lian Lim, Matt Davis, Robert Jedrzejewski, Ivo Busko
Author-email: help@stsci.edu
License: BSD
Platform: UNKNOWN
Classifier: Intended Audience :: Science/Research
Classifier: License :: OSI Approved :: BSD License
Classifier: Operating System :: OS Independent
Classifier: Programming Language :: Python
Classifier: Topic :: Scientific/Engineering :: Astronomy
Classifier: Topic :: Software Development :: Libraries :: Python Modules
Requires-Python: >=3.6
License-File: LICENSE.md
